{
  "1629460221": "https://cdn-rum.n2olabs.pro/stream.m3u8?url=https%3A%2F%2Flivecdn.rumsport.com%2Fstream%2F8%2Findex.m3u8&token=f24b353305ad7ade0a5c5d766debd519668e8f8b&is_vip=false&verify=1757030400-%2F1sb7S1rhxrYABXhFp%2F5UrcGuIDRfOBfliP494l5OLA%3D",
  "1397438": "https://cdn-rum.n2olabs.pro/stream.m3u8?url=https%3A%2F%2Flivecdn.rumsport.com%2Fstream%2F18%2Findex.m3u8&token=f24b353305ad7ade0a5c5d766debd519668e8f8b&is_vip=false&verify=1757030400-%2F1sb7S1rhxrYABXhFp%2F5UrcGuIDRfOBfliP494l5OLA%3D",
  "1629461047": "https://cdn-rum.n2olabs.pro/stream.m3u8?url=https%3A%2F%2Flivecdn.rumsport.com%2Fstream%2F8%2Findex.m3u8&token=f24b353305ad7ade0a5c5d766debd519668e8f8b&is_vip=false&verify=1757030400-%2F1sb7S1rhxrYABXhFp%2F5UrcGuIDRfOBfliP494l5OLA%3D",
  "1629460236": "https://cdn-rum.n2olabs.pro/stream.m3u8?url=https%3A%2F%2Flivecdn.rumsport.com%2Fstream%2F15%2Findex.m3u8&token=f24b353305ad7ade0a5c5d766debd519668e8f8b&is_vip=false&verify=1757030400-%2F1sb7S1rhxrYABXhFp%2F5UrcGuIDRfOBfliP494l5OLA%3D",
  "1629460234": "https://cdn-rum.n2olabs.pro/stream.m3u8?url=https%3A%2F%2Flivecdn.rumsport.com%2Fstream%2F48%2Findex.m3u8&token=f24b353305ad7ade0a5c5d766debd519668e8f8b&is_vip=false&verify=1757030400-%2F1sb7S1rhxrYABXhFp%2F5UrcGuIDRfOBfliP494l5OLA%3D"
}