{
  "1438727": "https://cdn-rum.n2olabs.pro/stream.m3u8?url=https%3A%2F%2Flivecdn.rumsport.com%2Fstream%2F15%2Findex.m3u8&token=b875d9fd466465ea3ceec715265168b879dc3686&is_vip=false&verify=1759168800-x3B0pRl5bhUIsH%2B23DliYV4wTQ8aAOBUP6hrO10lbzM%3D",
  "1391311": "https://cdn-rum.n2olabs.pro/stream.m3u8?url=https%3A%2F%2Flivecdn.rumsport.com%2Fstream%2F18%2Findex.m3u8&token=b875d9fd466465ea3ceec715265168b879dc3686&is_vip=false&verify=1759168800-x3B0pRl5bhUIsH%2B23DliYV4wTQ8aAOBUP6hrO10lbzM%3D",
  "1377906": "https://cdn-rum.n2olabs.pro/stream.m3u8?url=https%3A%2F%2Flivecdn.rumsport.com%2Fstream%2F6%2Findex.m3u8&token=b875d9fd466465ea3ceec715265168b879dc3686&is_vip=false&verify=1759168800-x3B0pRl5bhUIsH%2B23DliYV4wTQ8aAOBUP6hrO10lbzM%3D",
  "1396292": "https://cdn-rum.n2olabs.pro/stream.m3u8?url=https%3A%2F%2Flivecdn.rumsport.com%2Fstream%2F22%2Findex.m3u8&token=b875d9fd466465ea3ceec715265168b879dc3686&is_vip=false&verify=1759168800-x3B0pRl5bhUIsH%2B23DliYV4wTQ8aAOBUP6hrO10lbzM%3D",
  "1379023": "https://cdn-rum.n2olabs.pro/stream.m3u8?url=https%3A%2F%2Flivecdn.rumsport.com%2Fstream%2F17%2Findex.m3u8&token=b875d9fd466465ea3ceec715265168b879dc3686&is_vip=false&verify=1759168800-x3B0pRl5bhUIsH%2B23DliYV4wTQ8aAOBUP6hrO10lbzM%3D"
}