{
  "1629463080": "https://cdn-rum.n2olabs.pro/stream.m3u8?url=https%3A%2F%2Flivecdn.rumsport.com%2Fstream%2F38%2Findex.m3u8&token=d17c59ca88c2e6a7f1eb87c2c3d0586ff33d6672&is_vip=false&verify=1758369600-HjKP3%2BeTs1wx%2BH6%2B6CMe8qzBvdtn3lqW4wOI5OEJiWc%3D",
  "1388662": "https://cdn-rum.n2olabs.pro/stream.m3u8?url=https%3A%2F%2Flivecdn.rumsport.com%2Fstream%2F5%2Findex.m3u8&token=d17c59ca88c2e6a7f1eb87c2c3d0586ff33d6672&is_vip=false&verify=1758369600-HjKP3%2BeTs1wx%2BH6%2B6CMe8qzBvdtn3lqW4wOI5OEJiWc%3D",
  "1388664": "https://cdn-rum.n2olabs.pro/stream.m3u8?url=https%3A%2F%2Flivecdn.rumsport.com%2Fstream%2F6%2Findex.m3u8&token=d17c59ca88c2e6a7f1eb87c2c3d0586ff33d6672&is_vip=false&verify=1758369600-HjKP3%2BeTs1wx%2BH6%2B6CMe8qzBvdtn3lqW4wOI5OEJiWc%3D",
  "1388660": "https://cdn-rum.n2olabs.pro/stream.m3u8?url=https%3A%2F%2Flivecdn.rumsport.com%2Fstream%2F33%2Findex.m3u8&token=d17c59ca88c2e6a7f1eb87c2c3d0586ff33d6672&is_vip=false&verify=1758369600-HjKP3%2BeTs1wx%2BH6%2B6CMe8qzBvdtn3lqW4wOI5OEJiWc%3D",
  "1379014": "https://cdn-rum.n2olabs.pro/stream.m3u8?url=https%3A%2F%2Flivecdn.rumsport.com%2Fstream%2F27%2Findex.m3u8&token=d17c59ca88c2e6a7f1eb87c2c3d0586ff33d6672&is_vip=false&verify=1758369600-HjKP3%2BeTs1wx%2BH6%2B6CMe8qzBvdtn3lqW4wOI5OEJiWc%3D",
  "1386611": "https://cdn-rum.n2olabs.pro/stream.m3u8?url=https%3A%2F%2Flivecdn.rumsport.com%2Fstream%2F8%2Findex.m3u8&token=d17c59ca88c2e6a7f1eb87c2c3d0586ff33d6672&is_vip=false&verify=1758369600-HjKP3%2BeTs1wx%2BH6%2B6CMe8qzBvdtn3lqW4wOI5OEJiWc%3D",
  "1390863": "https://cdn-rum.n2olabs.pro/stream.m3u8?url=https%3A%2F%2Flivecdn.rumsport.com%2Fstream%2F25%2Findex.m3u8&token=d17c59ca88c2e6a7f1eb87c2c3d0586ff33d6672&is_vip=false&verify=1758369600-HjKP3%2BeTs1wx%2BH6%2B6CMe8qzBvdtn3lqW4wOI5OEJiWc%3D",
  "1401224": "https://cdn-rum.n2olabs.pro/stream.m3u8?url=https%3A%2F%2Flivecdn.rumsport.com%2Fstream%2F32%2Findex.m3u8&token=d17c59ca88c2e6a7f1eb87c2c3d0586ff33d6672&is_vip=false&verify=1758369600-HjKP3%2BeTs1wx%2BH6%2B6CMe8qzBvdtn3lqW4wOI5OEJiWc%3D",
  "1389166": "https://cdn-rum.n2olabs.pro/stream.m3u8?url=https%3A%2F%2Flivecdn.rumsport.com%2Fstream%2F44%2Findex.m3u8&token=d17c59ca88c2e6a7f1eb87c2c3d0586ff33d6672&is_vip=false&verify=1758369600-HjKP3%2BeTs1wx%2BH6%2B6CMe8qzBvdtn3lqW4wOI5OEJiWc%3D",
  "1629463004": "https://cdn-rum.n2olabs.pro/stream.m3u8?url=https%3A%2F%2Flivecdn.rumsport.com%2Fstream%2F45%2Findex.m3u8&token=d17c59ca88c2e6a7f1eb87c2c3d0586ff33d6672&is_vip=false&verify=1758369600-HjKP3%2BeTs1wx%2BH6%2B6CMe8qzBvdtn3lqW4wOI5OEJiWc%3D",
  "1380456": "https://cdn-rum.n2olabs.pro/stream.m3u8?url=https%3A%2F%2Flivecdn.rumsport.com%2Fstream%2F42%2Findex.m3u8&token=d17c59ca88c2e6a7f1eb87c2c3d0586ff33d6672&is_vip=false&verify=1758369600-HjKP3%2BeTs1wx%2BH6%2B6CMe8qzBvdtn3lqW4wOI5OEJiWc%3D",
  "1377894": "https://cdn-rum.n2olabs.pro/stream.m3u8?url=https%3A%2F%2Flivecdn.rumsport.com%2Fstream%2F3%2Findex.m3u8&token=d17c59ca88c2e6a7f1eb87c2c3d0586ff33d6672&is_vip=false&verify=1758369600-HjKP3%2BeTs1wx%2BH6%2B6CMe8qzBvdtn3lqW4wOI5OEJiWc%3D"
}