{
  "1629466930": "https://cdn-rum.n2olabs.pro/stream.m3u8?url=https%3A%2F%2Flivecdn.rumsport.com%2Fstream%2F5%2Findex.m3u8&token=f0b4618b4fccd769052e5c42e4fa12430676a874&is_vip=false&verify=1761156000-aC3u2dKThA%2BxN8Tj7N%2BonK6%2BkqqR7YUV78SX3oTp%2B9I%3D",
  "1629466931": "https://cdn-rum.n2olabs.pro/stream.m3u8?url=https%3A%2F%2Flivecdn.rumsport.com%2Fstream%2F46%2Findex.m3u8&token=f0b4618b4fccd769052e5c42e4fa12430676a874&is_vip=false&verify=1761156000-aC3u2dKThA%2BxN8Tj7N%2BonK6%2BkqqR7YUV78SX3oTp%2B9I%3D",
  "1629466943": "https://cdn-rum.n2olabs.pro/stream.m3u8?url=https%3A%2F%2Flivecdn.rumsport.com%2Fstream%2F18%2Findex.m3u8&token=f0b4618b4fccd769052e5c42e4fa12430676a874&is_vip=false&verify=1761156000-aC3u2dKThA%2BxN8Tj7N%2BonK6%2BkqqR7YUV78SX3oTp%2B9I%3D",
  "1629466942": "https://cdn-rum.n2olabs.pro/stream.m3u8?url=https%3A%2F%2Flivecdn.rumsport.com%2Fstream%2F39%2Findex.m3u8&token=f0b4618b4fccd769052e5c42e4fa12430676a874&is_vip=false&verify=1761156000-aC3u2dKThA%2BxN8Tj7N%2BonK6%2BkqqR7YUV78SX3oTp%2B9I%3D",
  "1629466941": "https://cdn-rum.n2olabs.pro/stream.m3u8?url=https%3A%2F%2Flivecdn.rumsport.com%2Fstream%2F38%2Findex.m3u8&token=f0b4618b4fccd769052e5c42e4fa12430676a874&is_vip=false&verify=1761156000-aC3u2dKThA%2BxN8Tj7N%2BonK6%2BkqqR7YUV78SX3oTp%2B9I%3D",
  "1629466944": "https://cdn-rum.n2olabs.pro/stream.m3u8?url=https%3A%2F%2Flivecdn.rumsport.com%2Fstream%2F20%2Findex.m3u8&token=f0b4618b4fccd769052e5c42e4fa12430676a874&is_vip=false&verify=1761156000-aC3u2dKThA%2BxN8Tj7N%2BonK6%2BkqqR7YUV78SX3oTp%2B9I%3D",
  "1386682": "https://cdn-rum.n2olabs.pro/stream.m3u8?url=https%3A%2F%2Flivecdn.rumsport.com%2Fstream%2F48%2Findex.m3u8&token=f0b4618b4fccd769052e5c42e4fa12430676a874&is_vip=false&verify=1761156000-aC3u2dKThA%2BxN8Tj7N%2BonK6%2BkqqR7YUV78SX3oTp%2B9I%3D",
  "1451071": "https://cdn-rum.n2olabs.pro/stream.m3u8?url=https%3A%2F%2Flivecdn.rumsport.com%2Fstream%2F27%2Findex.m3u8&token=f0b4618b4fccd769052e5c42e4fa12430676a874&is_vip=false&verify=1761156000-aC3u2dKThA%2BxN8Tj7N%2BonK6%2BkqqR7YUV78SX3oTp%2B9I%3D",
  "1451067": "https://cdn-rum.n2olabs.pro/stream.m3u8?url=https%3A%2F%2Flivecdn.rumsport.com%2Fstream%2F23%2Findex.m3u8&token=f0b4618b4fccd769052e5c42e4fa12430676a874&is_vip=false&verify=1761156000-aC3u2dKThA%2BxN8Tj7N%2BonK6%2BkqqR7YUV78SX3oTp%2B9I%3D",
  "1451068": "https://cdn-rum.n2olabs.pro/stream.m3u8?url=https%3A%2F%2Flivecdn.rumsport.com%2Fstream%2F25%2Findex.m3u8&token=f0b4618b4fccd769052e5c42e4fa12430676a874&is_vip=false&verify=1761156000-aC3u2dKThA%2BxN8Tj7N%2BonK6%2BkqqR7YUV78SX3oTp%2B9I%3D",
  "1386680": "https://cdn-rum.n2olabs.pro/stream.m3u8?url=https%3A%2F%2Flivecdn.rumsport.com%2Fstream%2F15%2Findex.m3u8&token=f0b4618b4fccd769052e5c42e4fa12430676a874&is_vip=false&verify=1761156000-aC3u2dKThA%2BxN8Tj7N%2BonK6%2BkqqR7YUV78SX3oTp%2B9I%3D",
  "1451072": "https://cdn-rum.n2olabs.pro/stream.m3u8?url=https%3A%2F%2Flivecdn.rumsport.com%2Fstream%2F33%2Findex.m3u8&token=f0b4618b4fccd769052e5c42e4fa12430676a874&is_vip=false&verify=1761156000-aC3u2dKThA%2BxN8Tj7N%2BonK6%2BkqqR7YUV78SX3oTp%2B9I%3D",
  "1451070": "https://cdn-rum.n2olabs.pro/stream.m3u8?url=https%3A%2F%2Flivecdn.rumsport.com%2Fstream%2F2%2Findex.m3u8&token=f0b4618b4fccd769052e5c42e4fa12430676a874&is_vip=false&verify=1761156000-aC3u2dKThA%2BxN8Tj7N%2BonK6%2BkqqR7YUV78SX3oTp%2B9I%3D",
  "1451073": "https://cdn-rum.n2olabs.pro/stream.m3u8?url=https%3A%2F%2Flivecdn.rumsport.com%2Fstream%2F6%2Findex.m3u8&token=f0b4618b4fccd769052e5c42e4fa12430676a874&is_vip=false&verify=1761156000-aC3u2dKThA%2BxN8Tj7N%2BonK6%2BkqqR7YUV78SX3oTp%2B9I%3D",
  "1451069": "https://cdn-rum.n2olabs.pro/stream.m3u8?url=https%3A%2F%2Flivecdn.rumsport.com%2Fstream%2F3_fhd%2Findex.m3u8&token=f0b4618b4fccd769052e5c42e4fa12430676a874&is_vip=false&verify=1761156000-aC3u2dKThA%2BxN8Tj7N%2BonK6%2BkqqR7YUV78SX3oTp%2B9I%3D"
}