{
  "1629469271": "https://cdn-rum.n2olabs.pro/stream.m3u8?url=https%3A%2F%2Flivecdn.rumsport.com%2Fstream%2F27%2Findex.m3u8&token=0359879104318e4e273eb465c6cd73248db47615&is_vip=false&verify=1762052400-VmfpVmJ%2BL1uGr6ZHtO9logH4KRWL%2FOT981anABXqsvI%3D",
  "1629468006": "https://cdn-rum.n2olabs.pro/stream.m3u8?url=https%3A%2F%2Flivecdn.rumsport.com%2Fstream%2F22%2Findex.m3u8&token=0359879104318e4e273eb465c6cd73248db47615&is_vip=false&verify=1762052400-VmfpVmJ%2BL1uGr6ZHtO9logH4KRWL%2FOT981anABXqsvI%3D",
  "1629468007": "https://cdn-rum.n2olabs.pro/stream.m3u8?url=https%3A%2F%2Flivecdn.rumsport.com%2Fstream%2F41%2Findex.m3u8&token=0359879104318e4e273eb465c6cd73248db47615&is_vip=false&verify=1762052400-VmfpVmJ%2BL1uGr6ZHtO9logH4KRWL%2FOT981anABXqsvI%3D",
  "1629468009": "https://cdn-rum.n2olabs.pro/stream.m3u8?url=https%3A%2F%2Flivecdn.rumsport.com%2Fstream%2F17%2Findex.m3u8&token=0359879104318e4e273eb465c6cd73248db47615&is_vip=false&verify=1762052400-VmfpVmJ%2BL1uGr6ZHtO9logH4KRWL%2FOT981anABXqsvI%3D",
  "1629468011": "https://cdn-rum.n2olabs.pro/stream.m3u8?url=https%3A%2F%2Flivecdn.rumsport.com%2Fstream%2F32%2Findex.m3u8&token=0359879104318e4e273eb465c6cd73248db47615&is_vip=false&verify=1762052400-VmfpVmJ%2BL1uGr6ZHtO9logH4KRWL%2FOT981anABXqsvI%3D",
  "1629468012": "https://cdn-rum.n2olabs.pro/stream.m3u8?url=https%3A%2F%2Flivecdn.rumsport.com%2Fstream%2F9%2Findex.m3u8&token=0359879104318e4e273eb465c6cd73248db47615&is_vip=false&verify=1762052400-VmfpVmJ%2BL1uGr6ZHtO9logH4KRWL%2FOT981anABXqsvI%3D",
  "1629468010": "https://cdn-rum.n2olabs.pro/stream.m3u8?url=https%3A%2F%2Flivecdn.rumsport.com%2Fstream%2F48%2Findex.m3u8&token=0359879104318e4e273eb465c6cd73248db47615&is_vip=false&verify=1762052400-VmfpVmJ%2BL1uGr6ZHtO9logH4KRWL%2FOT981anABXqsvI%3D",
  "1484475": "https://cdn-rum.n2olabs.pro/stream.m3u8?url=https%3A%2F%2Flivecdn.rumsport.com%2Fstream%2F6%2Findex.m3u8&token=0359879104318e4e273eb465c6cd73248db47615&is_vip=false&verify=1762052400-VmfpVmJ%2BL1uGr6ZHtO9logH4KRWL%2FOT981anABXqsvI%3D"
}