{
  "1629470644": "https://cdn-rum.n2olabs.pro/stream.m3u8?url=https%3A%2F%2Flivecdn.rumsport.com%2Fstream%2F35%2Findex.m3u8&token=ffb20b68c91ddb353e38afa9e3c6342e3b1e86d7&is_vip=false&verify=1763694000-jAdBs41mHoBY3VH%2BAbW%2FL%2BvwqwV44C%2FMJh%2BY64yq2Dc%3D",
  "1629470554": "https://cdn-rum.n2olabs.pro/stream.m3u8?url=https%3A%2F%2Flivecdn.rumsport.com%2Fstream%2F47%2Findex.m3u8&token=ffb20b68c91ddb353e38afa9e3c6342e3b1e86d7&is_vip=false&verify=1763694000-jAdBs41mHoBY3VH%2BAbW%2FL%2BvwqwV44C%2FMJh%2BY64yq2Dc%3D",
  "1629470647": "https://cdn-rum.n2olabs.pro/stream.m3u8?url=https%3A%2F%2Flivecdn.rumsport.com%2Fstream%2F38%2Findex.m3u8&token=ffb20b68c91ddb353e38afa9e3c6342e3b1e86d7&is_vip=false&verify=1763694000-jAdBs41mHoBY3VH%2BAbW%2FL%2BvwqwV44C%2FMJh%2BY64yq2Dc%3D",
  "1629470646": "https://cdn-rum.n2olabs.pro/stream.m3u8?url=https%3A%2F%2Flivecdn.rumsport.com%2Fstream%2F34%2Findex.m3u8&token=ffb20b68c91ddb353e38afa9e3c6342e3b1e86d7&is_vip=false&verify=1763694000-jAdBs41mHoBY3VH%2BAbW%2FL%2BvwqwV44C%2FMJh%2BY64yq2Dc%3D",
  "1629470645": "https://cdn-rum.n2olabs.pro/stream.m3u8?url=https%3A%2F%2Flivecdn.rumsport.com%2Fstream%2F33%2Findex.m3u8&token=ffb20b68c91ddb353e38afa9e3c6342e3b1e86d7&is_vip=false&verify=1763694000-jAdBs41mHoBY3VH%2BAbW%2FL%2BvwqwV44C%2FMJh%2BY64yq2Dc%3D",
  "1629470651": "https://cdn-rum.n2olabs.pro/stream.m3u8?url=https%3A%2F%2Flivecdn.rumsport.com%2Fstream%2F25_fhd%2Findex.m3u8&token=ffb20b68c91ddb353e38afa9e3c6342e3b1e86d7&is_vip=false&verify=1763694000-jAdBs41mHoBY3VH%2BAbW%2FL%2BvwqwV44C%2FMJh%2BY64yq2Dc%3D",
  "1629470652": "https://cdn-rum.n2olabs.pro/stream.m3u8?url=https%3A%2F%2Flivecdn.rumsport.com%2Fstream%2F45%2Findex.m3u8&token=ffb20b68c91ddb353e38afa9e3c6342e3b1e86d7&is_vip=false&verify=1763694000-jAdBs41mHoBY3VH%2BAbW%2FL%2BvwqwV44C%2FMJh%2BY64yq2Dc%3D"
}