{
  "1379103": "https://cdn-rum.n2olabs.pro/stream.m3u8?url=https%3A%2F%2Flivecdn.rumsport.com%2Fstream%2F27_fhd%2Findex.m3u8&token=5fac347e32df2fec7ca78872fa8d213ab680e1c9&is_vip=false&verify=1764709200-wMGbVF7vS1%2F%2BRz8WWlX919K2ZYbVfr3xOAj7%2Fl0V4Go%3D",
  "1629472018": "https://cdn-rum.n2olabs.pro/stream.m3u8?url=https%3A%2F%2Flivecdn.rumsport.com%2Fstream%2F34%2Findex.m3u8&token=5fac347e32df2fec7ca78872fa8d213ab680e1c9&is_vip=false&verify=1764709200-wMGbVF7vS1%2F%2BRz8WWlX919K2ZYbVfr3xOAj7%2Fl0V4Go%3D",
  "1379100": "https://cdn-rum.n2olabs.pro/stream.m3u8?url=https%3A%2F%2Flivecdn.rumsport.com%2Fstream%2F15%2Findex.m3u8&token=5fac347e32df2fec7ca78872fa8d213ab680e1c9&is_vip=false&verify=1764709200-wMGbVF7vS1%2F%2BRz8WWlX919K2ZYbVfr3xOAj7%2Fl0V4Go%3D",
  "1485258": "https://cdn-rum.n2olabs.pro/stream.m3u8?url=https%3A%2F%2Flivecdn.rumsport.com%2Fstream%2F3%2Findex.m3u8&token=5fac347e32df2fec7ca78872fa8d213ab680e1c9&is_vip=false&verify=1764709200-wMGbVF7vS1%2F%2BRz8WWlX919K2ZYbVfr3xOAj7%2Fl0V4Go%3D",
  "1485262": "https://cdn-rum.n2olabs.pro/stream.m3u8?url=https%3A%2F%2Flivecdn.rumsport.com%2Fstream%2F22%2Findex.m3u8&token=5fac347e32df2fec7ca78872fa8d213ab680e1c9&is_vip=false&verify=1764709200-wMGbVF7vS1%2F%2BRz8WWlX919K2ZYbVfr3xOAj7%2Fl0V4Go%3D",
  "1477052": "https://cdn-rum.n2olabs.pro/stream.m3u8?url=https%3A%2F%2Flivecdn.rumsport.com%2Fstream%2F40%2Findex.m3u8&token=5fac347e32df2fec7ca78872fa8d213ab680e1c9&is_vip=false&verify=1764709200-wMGbVF7vS1%2F%2BRz8WWlX919K2ZYbVfr3xOAj7%2Fl0V4Go%3D",
  "1391000": "https://cdn-rum.n2olabs.pro/stream.m3u8?url=https%3A%2F%2Flivecdn.rumsport.com%2Fstream%2F25_fhd%2Findex.m3u8&token=5fac347e32df2fec7ca78872fa8d213ab680e1c9&is_vip=false&verify=1764709200-wMGbVF7vS1%2F%2BRz8WWlX919K2ZYbVfr3xOAj7%2Fl0V4Go%3D",
  "1486141": "https://cdn-rum.n2olabs.pro/stream.m3u8?url=https%3A%2F%2Flivecdn.rumsport.com%2Fstream%2F32%2Findex.m3u8&token=5fac347e32df2fec7ca78872fa8d213ab680e1c9&is_vip=false&verify=1764709200-wMGbVF7vS1%2F%2BRz8WWlX919K2ZYbVfr3xOAj7%2Fl0V4Go%3D",
  "1379107": "https://cdn-rum.n2olabs.pro/stream.m3u8?url=https%3A%2F%2Flivecdn.rumsport.com%2Fstream%2F24%2Findex.m3u8&token=5fac347e32df2fec7ca78872fa8d213ab680e1c9&is_vip=false&verify=1764709200-wMGbVF7vS1%2F%2BRz8WWlX919K2ZYbVfr3xOAj7%2Fl0V4Go%3D",
  "1629471530": "https://cdn-rum.n2olabs.pro/stream.m3u8?url=https%3A%2F%2Flivecdn.rumsport.com%2Fstream%2F38%2Findex.m3u8&token=5fac347e32df2fec7ca78872fa8d213ab680e1c9&is_vip=false&verify=1764709200-wMGbVF7vS1%2F%2BRz8WWlX919K2ZYbVfr3xOAj7%2Fl0V4Go%3D"
}