{
  "1629464517": "https://cdn-rum.n2olabs.pro/stream.m3u8?url=https%3A%2F%2Flivecdn.rumsport.com%2Fstream%2F46%2Findex.m3u8&token=19d493a28334e253030ba7fec3415037b419470e&is_vip=false&verify=1760108400-OCjjGI1I94JPzf3%2FeYHJWPzjbsMKgENtm%2F5%2Bj%2FrN55s%3D",
  "1629465695": "https://cdn-rum.n2olabs.pro/stream.m3u8?url=https%3A%2F%2Flivecdn.rumsport.com%2Fstream%2F38%2Findex.m3u8&token=19d493a28334e253030ba7fec3415037b419470e&is_vip=false&verify=1760108400-OCjjGI1I94JPzf3%2FeYHJWPzjbsMKgENtm%2F5%2Bj%2FrN55s%3D",
  "1629464516": "https://cdn-rum.n2olabs.pro/stream.m3u8?url=https%3A%2F%2Flivecdn.rumsport.com%2Fstream%2F32%2Findex.m3u8&token=19d493a28334e253030ba7fec3415037b419470e&is_vip=false&verify=1760108400-OCjjGI1I94JPzf3%2FeYHJWPzjbsMKgENtm%2F5%2Bj%2FrN55s%3D",
  "1126068": "https://cdn-rum.n2olabs.pro/stream.m3u8?url=https%3A%2F%2Flivecdn.rumsport.com%2Fstream%2F8%2Findex.m3u8&token=19d493a28334e253030ba7fec3415037b419470e&is_vip=false&verify=1760108400-OCjjGI1I94JPzf3%2FeYHJWPzjbsMKgENtm%2F5%2Bj%2FrN55s%3D",
  "1629465696": "https://cdn-rum.n2olabs.pro/stream.m3u8?url=https%3A%2F%2Flivecdn.rumsport.com%2Fstream%2F48%2Findex.m3u8&token=19d493a28334e253030ba7fec3415037b419470e&is_vip=false&verify=1760108400-OCjjGI1I94JPzf3%2FeYHJWPzjbsMKgENtm%2F5%2Bj%2FrN55s%3D",
  "1126069": "https://cdn-rum.n2olabs.pro/stream.m3u8?url=https%3A%2F%2Flivecdn.rumsport.com%2Fstream%2F1%2Findex.m3u8&token=19d493a28334e253030ba7fec3415037b419470e&is_vip=false&verify=1760108400-OCjjGI1I94JPzf3%2FeYHJWPzjbsMKgENtm%2F5%2Bj%2FrN55s%3D",
  "1126070": "https://cdn-rum.n2olabs.pro/stream.m3u8?url=https%3A%2F%2Flivecdn.rumsport.com%2Fstream%2F24%2Findex.m3u8&token=19d493a28334e253030ba7fec3415037b419470e&is_vip=false&verify=1760108400-OCjjGI1I94JPzf3%2FeYHJWPzjbsMKgENtm%2F5%2Bj%2FrN55s%3D"
}